<?xml version="1.0" encoding="utf-8"?>
<!DOCTYPE hibernate-mapping PUBLIC "-//Hibernate/Hibernate Mapping DTD 3.0//EN"
"http://hibernate.sourceforge.net/hibernate-mapping-3.0.dtd">
<!-- 
    Mapping file autogenerated by MyEclipse Persistence Tools
-->
<hibernate-mapping>
    <class name="com.zjkj.wxy.core.domain.Communication" table="t_communication" >
        <id name="id" type="java.lang.Integer">
            <column name="ID" precision="22" scale="0"/>
            <generator class="native"/>
        </id>
        <many-to-one name="user" class="com.zjkj.wxy.core.domain.User" fetch="select">
            <column name="uid" precision="22" scale="0" />
        </many-to-one>
        <property name="time" type="java.lang.Long">
            <column name="TIME" precision="22" scale="0" />
        </property>
        <property name="stuname" type="java.lang.String">
            <column name="STUNAME" length="15" />
        </property>
        <property name="edunum" type="java.lang.String">
            <column name="EDUNUM" length="15" />
        </property>
        <property name="parname" type="java.lang.String">
            <column name="PARNAME" length="15" />
        </property>
        <property name="parphnum" type="java.lang.String">
            <column name="PARPHNUM" length="15" />
        </property>
        <property name="commtype" type="java.lang.Integer">
            <column name="COMMTYPE" precision="22" scale="0" />
        </property>
        <property name="commcont" type="java.lang.String">
            <column name="COMMCONT" length="300" />
        </property>
    </class>
</hibernate-mapping>
